Metadata-Version: 2.1
Name: odoo14-addon-base_ubl_payment
Version: 14.0.1.0.1.dev15
Summary: Payment-related code for Universal Business Language (UBL)
Home-page: https://github.com/OCA/edi
Author: Akretion,Odoo Community Association (OCA)
Author-email: support@odoo-community.org
License: AGPL-3
Classifier: Programming Language :: Python
Classifier: Framework :: Odoo
Classifier: Framework :: Odoo :: 14.0
Classifier: License :: OSI Approved :: GNU Affero General Public License v3
Requires-Python: >=3.6
Requires-Dist: odoo14-addon-account-payment-unece
Requires-Dist: odoo14-addon-base-ubl
Requires-Dist: odoo<14.1dev,>=14.0a
